LICENSE
MANIFEST.in
README.rst
setup.cfg
setup.py
versioneer.py
wavy/__init__.py
wavy/_version.py
wavy/exceptions.py
wavy/info.py
wavy/read.py
wavy/tags.py
wavy/wave_file.py
wavy.egg-info/PKG-INFO
wavy.egg-info/SOURCES.txt
wavy.egg-info/dependency_links.txt
wavy.egg-info/requires.txt
wavy.egg-info/top_level.txt
wavy/detail/__init__.py
wavy/detail/common.py
wavy/detail/read.py
wavy/detail/stream_handler.py