Metadata-Version: 1.1
Name: wavy
Version: 0.1.2
Summary: A pure python module for working with WAVE files with support for all common file formats for both RIFF and RIFX.
Home-page: https://github.com/acelletti/wavy
Author: Andrea Celletti
Author-email: celletti.andrea87@gmail.com
License: UNKNOWN
Keywords: audio wave wav
Platform: UNKNOWN
Classifier: Development Status :: 3 - Alpha
Classifier: Intended Audience :: Developers
Classifier: Topic :: Multimedia :: Sound/Audio
Classifier: License :: OSI Approved :: MIT License
Classifier: Programming Language :: Python :: 3
Classifier: Programming Language :: Python :: 3.4
Classifier: Programming Language :: Python :: 3.5
Classifier: Programming Language :: Python :: 3.6
